mu/__init__.py
mu/config.py
mu/exc.py
mu/handler.py
mu/tasks.py
mu/version.py
mu/cli/__init__.py
mu/cli/aws.py
mu/cli/core.py
mu/handlers/diagnostics.py
mu/libs/__init__.py
mu/libs/api_gateway.py
mu/libs/auth.py
mu/libs/aws_recs.py
mu/libs/concurrent.py
mu/libs/ec2.py
mu/libs/ecr.py
mu/libs/ecs.py
mu/libs/gateway.py
mu/libs/iam.py
mu/libs/lamb.py
mu/libs/logs.py
mu/libs/orgs.py
mu/libs/sqs.py
mu/libs/status.py
mu/libs/sts.py
mu/libs/testing.py
mu/libs/utils.py
aws_mu-0.20251205.5.dist-info/METADATA
aws_mu-0.20251205.5.dist-info/WHEEL
aws_mu-0.20251205.5.dist-info/entry_points.txt
aws_mu-0.20251205.5.dist-info/RECORD
