Metadata-Version: 2.4
Name: aws-mu
Version: 0.20251205.5
Author-email: Randy Syring <randy.syring@level12.io>
Requires-Python: >=3.12
Requires-Dist: arrow>=1.3.0
Requires-Dist: awsgi2>=1.0.2
Requires-Dist: blazeutils>=0.7.0
Requires-Dist: boto3>=1.38.34
Requires-Dist: click>=8.2.1
Requires-Dist: colorlog>=6.9.0
Requires-Dist: cryptography>=45.0.4
Requires-Dist: docker>=7.1.0
Requires-Dist: methodtools>=0.4.7
Requires-Dist: requests>=2.32.4
